odoo/addons/product_code_mandatory/README.rst
odoo/addons/product_code_mandatory/__init__.py
odoo/addons/product_code_mandatory/__manifest__.py
odoo/addons/product_code_mandatory/data/product_code_seq.xml
odoo/addons/product_code_mandatory/i18n/ca.po
odoo/addons/product_code_mandatory/i18n/es.po
odoo/addons/product_code_mandatory/i18n/it.po
odoo/addons/product_code_mandatory/i18n/product_code_mandatory.pot
odoo/addons/product_code_mandatory/i18n/pt.po
odoo/addons/product_code_mandatory/models/__init__.py
odoo/addons/product_code_mandatory/models/product.py
odoo/addons/product_code_mandatory/readme/CONTRIBUTORS.rst
odoo/addons/product_code_mandatory/readme/DESCRIPTION.rst
odoo/addons/product_code_mandatory/readme/USAGE.rst
odoo/addons/product_code_mandatory/static/description/icon.png
odoo/addons/product_code_mandatory/static/description/index.html
odoo/addons/product_code_mandatory/tests/__init__.py
odoo/addons/product_code_mandatory/tests/test_product_code.py
odoo/addons/product_code_mandatory/views/product_view.xml
odoo12_addon_product_code_mandatory-12.0.1.0.0.99.dev12.dist-info/METADATA
odoo12_addon_product_code_mandatory-12.0.1.0.0.99.dev12.dist-info/WHEEL
odoo12_addon_product_code_mandatory-12.0.1.0.0.99.dev12.dist-info/top_level.txt
odoo12_addon_product_code_mandatory-12.0.1.0.0.99.dev12.dist-info/RECORD
